tests/__init__.py
tests/helpers.py
tests/test_callbacks.py
tests/test_loggers.py
tests/test_optimizers.py
tests/test_schedulers.py
tests/datamodules/__init__.py
tests/datamodules/helpers.py
tests/datamodules/test_datamodule_cpu.py
tests/datamodules/test_datamodule_ddp.py
tests/datamodules/test_datamodule_gpu.py
tests/datamodules/test_datamodule_mps.py
tests/language_models/__init__.py
tests/language_models/test_mlm.py
tests/language_models/test_rts.py
tests/language_models/test_solm.py
tests/language_models/test_swlm.py
tests/models/__init__.py
tests/models/helpers.py
tests/models/test_models_cpu.py
tests/models/test_models_ddp.py
tests/models/test_models_deepspeed.py
tests/models/test_models_gpu.py
transformers_lightning/__init__.py
transformers_lightning/info.py
transformers_lightning/adapters/__init__.py
transformers_lightning/adapters/csv_adapter.py
transformers_lightning/adapters/file_adapter.py
transformers_lightning/adapters/line_adapter.py
transformers_lightning/adapters/super_adapter.py
transformers_lightning/callbacks/__init__.py
transformers_lightning/callbacks/rich_progress_bar.py
transformers_lightning/callbacks/transformers_model_checkpoint.py
transformers_lightning/datamodules/__init__.py
transformers_lightning/datamodules/adapter_datamodule.py
transformers_lightning/datamodules/super_datamodule.py
transformers_lightning/datasets/__init__.py
transformers_lightning/datasets/iterable_dataset.py
transformers_lightning/datasets/map_dataset.py
transformers_lightning/datasets/stack_dataset.py
transformers_lightning/datasets/super_dataset.py
transformers_lightning/defaults/__init__.py
transformers_lightning/language_modeling/__init__.py
transformers_lightning/language_modeling/language_model.py
transformers_lightning/language_modeling/masked_language_modeling.py
transformers_lightning/language_modeling/random_token_substitution.py
transformers_lightning/language_modeling/sorting_language_modeling.py
transformers_lightning-0.7.12.dist-info/LICENSE
transformers_lightning-0.7.12.dist-info/METADATA
transformers_lightning-0.7.12.dist-info/WHEEL
transformers_lightning-0.7.12.dist-info/top_level.txt
transformers_lightning-0.7.12.dist-info/RECORD
