Metadata-Version: 2.1
Name: transformers-lightning
Version: 0.7.12
Summary: Easily deploy Transformers models over Lightning
Home-page: https://github.com/lucadiliello/transformers-lightning.git
Author: Luca Di Liello
Author-email: luca.diliello@unitn.it
License: GNU v2
Platform: UNKNOWN
Classifier: Programming Language :: Python :: 3
Classifier: License :: OSI Approved :: GNU General Public License v2 (GPLv2)
Classifier: Operating System :: OS Independent
Classifier: Development Status :: 4 - Beta
Classifier: Natural Language :: English
License-File: LICENSE
